datadelve/__init__.py
datadelve/exceptions.py
datadelve/main.py
datadelve-0.8.4.dist-info/LICENSE
datadelve-0.8.4.dist-info/WHEEL
datadelve-0.8.4.dist-info/METADATA
datadelve-0.8.4.dist-info/RECORD
